mapboxgl_notebook/__init__.py
mapboxgl_notebook/interactions.py
mapboxgl_notebook/layers.py
mapboxgl_notebook/map.py
mapboxgl_notebook/properties.py
mapboxgl_notebook/sources.py
mapboxgl_notebook/styles.py
mapboxgl_notebook/templates.py
mapboxgl_notebook/templates/base.html
mapboxgl_notebook/templates/map.html
mapboxgl_notebook-0.7.dist-info/LICENSE
mapboxgl_notebook-0.7.dist-info/METADATA
mapboxgl_notebook-0.7.dist-info/WHEEL
mapboxgl_notebook-0.7.dist-info/top_level.txt
mapboxgl_notebook-0.7.dist-info/RECORD
