Metadata-Version: 2.1
Name: mapboxgl-notebook
Version: 0.7
Summary: MapboxGL ipython renderer
Home-page: https://github.com/emakarov/mapboxgl_notebook
Author: Evgeni Makarov
Author-email: evgeni.makarov@gmail.com
License: BSD License
Platform: UNKNOWN
Classifier: Programming Language :: Python :: 3
Classifier: Intended Audience :: Developers
Classifier: Intended Audience :: Science/Research
Classifier: License :: OSI Approved :: MIT License
Classifier: Topic :: Multimedia :: Graphics :: Graphics Conversion
Classifier: Topic :: Scientific/Engineering :: GIS
Requires-Dist: mapboxgl
Requires-Dist: IPython
Requires-Dist: jinja2
Requires-Dist: nssjson
